dynami/__init__.py
dynami/dynami.py
dynami/ext/__init__.py
dynami/ext/client.py
dynami/ext/utils/__init__.py
dynami/ext/utils/config.py
dynami/ext/utils/ip.py
dynami/ext/utils/system.py
dynami/provider/__init__.py
dynami/provider/gcp.py
dynami/provider/godaddy.py
dynami/provider/hetzner.py
dynami-1.0.7.dist-info/LICENSE
dynami-1.0.7.dist-info/METADATA
dynami-1.0.7.dist-info/WHEEL
dynami-1.0.7.dist-info/entry_points.txt
dynami-1.0.7.dist-info/top_level.txt
dynami-1.0.7.dist-info/RECORD
