Metadata-Version: 2.1
Name: dynami
Version: 1.0.7
Summary: Module to dynamically update DNS records from multiple services like Hetzner, Amazon, Microsoft... 
Home-page: https://github.com/bytesentinel/dynami
Author: ByteSentinel
Author-email: info@bytesentinel.io
Classifier: Programming Language :: Python :: 3
Classifier: License :: OSI Approved :: MIT License
Classifier: Operating System :: OS Independent
Requires-Python: >=3.7
License-File: LICENSE
Requires-Dist: enumy (>=1.0.2)
Requires-Dist: google-cloud-dns (>=0.34.1)
